{
    "Manchester United": "https://media.api-sports.io/football/teams/33.png",
    "Newcastle": "https://media.api-sports.io/football/teams/34.png",
    "Bournemouth": "https://media.api-sports.io/football/teams/35.png",
    "Watford": "https://media.api-sports.io/football/teams/38.png",
    "Wolverhampton": "https://media.api-sports.io/football/teams/39.png",
    "Liverpool": "https://media.api-sports.io/football/teams/40.png",
    "Southampton": "https://media.api-sports.io/football/teams/41.png",
    "Arsenal": "https://media.api-sports.io/football/teams/42.png",
    "Burnley": "https://media.api-sports.io/football/teams/44.png",
    "Everton": "https://media.api-sports.io/football/teams/45.png",
    "Leicester City": "https://media.api-sports.io/football/teams/46.png",
    "Tottenham Hotspur": "https://media.api-sports.io/football/teams/47.png",
    "West Ham United": "https://media.api-sports.io/football/teams/48.png",
    "Chelsea": "https://media.api-sports.io/football/teams/49.png",
    "Manchester City": "https://media.api-sports.io/football/teams/50.png",
    "Brighton and Hove Albion": "https://media.api-sports.io/football/teams/51.png",
    "Crystal Palace": "https://media.api-sports.io/football/teams/52.png",
    "Sheffield Utd": "https://media.api-sports.io/football/teams/62.png",
    "Aston Villa": "https://media.api-sports.io/football/teams/66.png",
    "Norwich City": "https://media.api-sports.io/football/teams/71.png",
    "Bayern Munich": "https://media.api-sports.io/football/teams/157.png",
    "Fortuna Dusseldorf": "https://media.api-sports.io/football/teams/158.png",
    "Hertha Berlin": "https://media.api-sports.io/football/teams/159.png",
    "SC Freiburg": "https://media.api-sports.io/football/teams/160.png",
    "VfL Wolfsburg": "https://media.api-sports.io/football/teams/161.png",
    "Werder Bremen": "https://media.api-sports.io/football/teams/162.png",
    "Borussia Monchengladbach": "https://media.api-sports.io/football/teams/163.png",
    "FSV Mainz 05": "https://media.api-sports.io/football/teams/164.png",
    "Borussia Dortmund": "https://media.api-sports.io/football/teams/165.png",
    "1899 Hoffenheim": "https://media.api-sports.io/football/teams/167.png",
    "Bayer Leverkusen": "https://media.api-sports.io/football/teams/168.png",
    "Eintracht Frankfurt": "https://media.api-sports.io/football/teams/169.png",
    "FC Augsburg": "https://media.api-sports.io/football/teams/170.png",
    "RB Leipzig": "https://media.api-sports.io/football/teams/173.png",
    "FC Schalke 04": "https://media.api-sports.io/football/teams/174.png",
    "FC Heidenheim": "https://media.api-sports.io/football/teams/180.png",
    "Union Berlin": "https://media.api-sports.io/football/teams/182.png",
    "SC Paderborn 07": "https://media.api-sports.io/football/teams/185.png",
    "FC Koln": "https://media.api-sports.io/football/teams/192.png",
    "Barcelona": "https://media.api-sports.io/football/teams/529.png",
    "Atletico Madrid": "https://media.api-sports.io/football/teams/530.png",
    "Athletic Club": "https://media.api-sports.io/football/teams/531.png",
    "Valencia": "https://media.api-sports.io/football/teams/532.png",
    "Villarreal": "https://media.api-sports.io/football/teams/533.png",
    "Sevilla FC": "https://media.api-sports.io/football/teams/536.png",
    "Leganes": "https://media.api-sports.io/football/teams/537.png",
    "Celta Vigo": "https://media.api-sports.io/football/teams/538.png",
    "Levante": "https://media.api-sports.io/football/teams/539.png",
    "Espanyol": "https://media.api-sports.io/football/teams/540.png",
    "Real Madrid": "https://media.api-sports.io/football/teams/541.png",
    "Alavés": "https://media.api-sports.io/football/teams/542.png",
    "Real Betis": "https://media.api-sports.io/football/teams/543.png",
    "Eibar": "https://media.api-sports.io/football/teams/545.png",
    "Getafe": "https://media.api-sports.io/football/teams/546.png",
    "Real Sociedad": "https://media.api-sports.io/football/teams/548.png",
    "Granada": "https://media.api-sports.io/football/teams/715.png",
    "Valladolid": "https://media.api-sports.io/football/teams/720.png",
    "Osasuna": "https://media.api-sports.io/football/teams/727.png",
    "Mallorca": "https://media.api-sports.io/football/teams/798.png",
    "Diables Noirs": "https://media.api-sports.io/football/teams/3170.png",
    "Ot\u00f4ho d'Oyo": "https://media.api-sports.io/football/teams/6428.png",
    "\u00c9toile du Congo": "https://media.api-sports.io/football/teams/8077.png",
    "CARA Brazzaville": "https://media.api-sports.io/football/teams/8082.png",
    "L\u00e9opards de Dolisi\u00e9": "https://media.api-sports.io/football/teams/8105.png",
    "Cheminots": "https://media.api-sports.io/football/teams/10659.png",
    "Inter Club": "https://media.api-sports.io/football/teams/16791.png",
    "JS Talanga\u00ef": "https://media.api-sports.io/football/teams/16792.png",
    "Kondzo": "https://media.api-sports.io/football/teams/16793.png",
    "Nathaly's": "https://media.api-sports.io/football/teams/16794.png",
    "Nico-Nicoy\u00e9": "https://media.api-sports.io/football/teams/16795.png",
    "Patronage Sainte-Anne": "https://media.api-sports.io/football/teams/16796.png",
    "V.Club Mokanda": "https://media.api-sports.io/football/teams/16798.png",
    "Nouvelle G\u00e9n\u00e9ration": "https://media.api-sports.io/football/teams/18188.png",
    "Emelec": "https://media.api-sports.io/football/teams/1148.png",
    "Delfin SC": "https://media.api-sports.io/football/teams/1149.png",
    "Tecnico Universitario": "https://media.api-sports.io/football/teams/1151.png",
    "Barcelona SC": "https://media.api-sports.io/football/teams/1152.png",
    "Independiente del Valle": "https://media.api-sports.io/football/teams/1153.png",
    "Deportivo Cuenca": "https://media.api-sports.io/football/teams/1154.png",
    "Macara": "https://media.api-sports.io/football/teams/1155.png",
    "Aucas": "https://media.api-sports.io/football/teams/1156.png",
    "Universidad Catolica": "https://media.api-sports.io/football/teams/1157.png",
    "LDU de Quito": "https://media.api-sports.io/football/teams/1158.png",
    "Guayaquil City FC": "https://media.api-sports.io/football/teams/1159.png",
    "Mushuc Runa SC": "https://media.api-sports.io/football/teams/1162.png",
    "Gualaceo SC": "https://media.api-sports.io/football/teams/1986.png",
    "Orense SC": "https://media.api-sports.io/football/teams/1992.png",
    "9 de Octubre": "https://media.api-sports.io/football/teams/10111.png",
    "Cumbay\u00e1": "https://media.api-sports.io/football/teams/16476.png",
    "Gvardeyets": "https://media.api-sports.io/football/teams/17679.png",
    "Kyzyltash": "https://media.api-sports.io/football/teams/17680.png",
    "Ocean Kerch": "https://media.api-sports.io/football/teams/17681.png",
    "Rubin Yalta": "https://media.api-sports.io/football/teams/17682.png",
    "SKCHF Sevastopol": "https://media.api-sports.io/football/teams/17683.png",
    "TSK Simferopol": "https://media.api-sports.io/football/teams/17684.png",
    "Yevpatoriya": "https://media.api-sports.io/football/teams/17685.png",
    "Alushta": "https://media.api-sports.io/football/teams/17686.png",
    "FC Sevastopol": "https://media.api-sports.io/football/teams/18937.png",
    "VfB Stuttgart": "https://media.api-sports.io/football/teams/172.png",
    "VfL BOCHUM": "https://media.api-sports.io/football/teams/176.png",
    "SpVgg Greuther Furth": "https://media.api-sports.io/football/teams/178.png",
    "Arminia Bielefeld": "https://media.api-sports.io/football/teams/188.png",
    "PEC Zwolle": "https://media.api-sports.io/football/teams/193.png",
    "Ajax": "https://media.api-sports.io/football/teams/194.png",
    "Willem II": "https://media.api-sports.io/football/teams/195.png",
    "PSV Eindhoven": "https://media.api-sports.io/football/teams/197.png",
    "Vitesse": "https://media.api-sports.io/football/teams/200.png",
    "AZ Alkmaar": "https://media.api-sports.io/football/teams/201.png",
    "Groningen": "https://media.api-sports.io/football/teams/202.png",
    "Fortuna Sittard": "https://media.api-sports.io/football/teams/205.png",
    "Heracles": "https://media.api-sports.io/football/teams/206.png",
    "Utrecht": "https://media.api-sports.io/football/teams/207.png",
    "Feyenoord": "https://media.api-sports.io/football/teams/209.png",
    "Heerenveen": "https://media.api-sports.io/football/teams/210.png",
    "GO Ahead Eagles": "https://media.api-sports.io/football/teams/410.png",
    "NEC Nijmegen": "https://media.api-sports.io/football/teams/413.png",
    "Twente": "https://media.api-sports.io/football/teams/415.png",
    "Waalwijk": "https://media.api-sports.io/football/teams/417.png",
    "Cambuur": "https://media.api-sports.io/football/teams/420.png",
    "Sparta Rotterdam": "https://media.api-sports.io/football/teams/426.png",
    "Benfica": "https://media.api-sports.io/football/teams/211.png",
    "FC Porto": "https://media.api-sports.io/football/teams/212.png",
    "Maritimo": "https://media.api-sports.io/football/teams/214.png",
    "Moreirense": "https://media.api-sports.io/football/teams/215.png",
    "Portimonense": "https://media.api-sports.io/football/teams/216.png",
    "SC Braga": "https://media.api-sports.io/football/teams/217.png",
    "Tondela": "https://media.api-sports.io/football/teams/218.png",
    "Belenenses": "https://media.api-sports.io/football/teams/221.png",
    "Boavista": "https://media.api-sports.io/football/teams/222.png",
    "Guimaraes": "https://media.api-sports.io/football/teams/224.png",
    "Santa Clara": "https://media.api-sports.io/football/teams/227.png",
    "Sporting CP": "https://media.api-sports.io/football/teams/228.png",
    "Estoril": "https://media.api-sports.io/football/teams/230.png",
    "Pacos Ferreira": "https://media.api-sports.io/football/teams/234.png",
    "Arouca": "https://media.api-sports.io/football/teams/240.png",
    "Famalicao": "https://media.api-sports.io/football/teams/242.png",
    "GIL Vicente": "https://media.api-sports.io/football/teams/762.png",
    "Vizela": "https://media.api-sports.io/football/teams/810.png",
    "Cadiz": "https://media.api-sports.io/football/teams/724.png",
    "Rayo Vallecano": "https://media.api-sports.io/football/teams/728.png",
    "Elche": "https://media.api-sports.io/football/teams/797.png",
    "Linfield": "https://media.api-sports.io/football/teams/583.png",
    "Ballymena United": "https://media.api-sports.io/football/teams/668.png",
    "Coleraine FC": "https://media.api-sports.io/football/teams/669.png",
    "Crusaders FC": "https://media.api-sports.io/football/teams/697.png",
    "Cliftonville FC": "https://media.api-sports.io/football/teams/2266.png",
    "Glenavon FC": "https://media.api-sports.io/football/teams/2275.png",
    "Portadown": "https://media.api-sports.io/football/teams/5348.png",
    "Carrick Rangers": "https://media.api-sports.io/football/teams/5350.png",
    "Dungannon Swifts": "https://media.api-sports.io/football/teams/5351.png",
    "Glentoran": "https://media.api-sports.io/football/teams/5352.png",
    "Larne": "https://media.api-sports.io/football/teams/5354.png",
    "Warrenpoint Town": "https://media.api-sports.io/football/teams/5355.png",
    "Annagh United": "https://media.api-sports.io/football/teams/11109.png",
    "Lille": "https://media.api-sports.io/football/teams/79.png",
    "Paris Saint Germain": "https://media.api-sports.io/football/teams/85.png",
    "Monaco": "https://media.api-sports.io/football/teams/91.png",
    "Celtic": "https://media.api-sports.io/football/teams/247.png",
    "Rangers": "https://media.api-sports.io/football/teams/257.png",
    "Valur Reykjavik": "https://media.api-sports.io/football/teams/274.png",
    "Bodo/Glimt": "https://media.api-sports.io/football/teams/327.png",
    "Legia Warszawa": "https://media.api-sports.io/football/teams/339.png",
    "GAP Connah S Quay FC": "https://media.api-sports.io/football/teams/357.png",
    "Malmo FF": "https://media.api-sports.io/football/teams/375.png",
    "Shakhter Soligorsk": "https://media.api-sports.io/football/teams/392.png",
    "FC Midtjylland": "https://media.api-sports.io/football/teams/397.png",
    "Brondby": "https://media.api-sports.io/football/teams/407.png",
    "AC Milan": "https://media.api-sports.io/football/teams/489.png",
    "Juventus": "https://media.api-sports.io/football/teams/496.png",
    "Atalanta": "https://media.api-sports.io/football/teams/499.png",
    "Inter": "https://media.api-sports.io/football/teams/505.png",
    "Besiktas": "https://media.api-sports.io/football/teams/549.png",
    "Shakhtar Donetsk": "https://media.api-sports.io/football/teams/550.png",
    "Olympiakos Piraeus": "https://media.api-sports.io/football/teams/553.png",
    "Spartak Moscow": "https://media.api-sports.io/football/teams/558.png",
    "Slavia Praha": "https://media.api-sports.io/football/teams/560.png",
    "BSC Young Boys": "https://media.api-sports.io/football/teams/565.png",
    "Ludogorets": "https://media.api-sports.io/football/teams/566.png",
    "Sheriff Tiraspol": "https://media.api-sports.io/football/teams/568.png",
    "Club Brugge KV": "https://media.api-sports.io/football/teams/569.png",
    "Red Bull Salzburg": "https://media.api-sports.io/football/teams/571.png",
    "Dynamo Kyiv": "https://media.api-sports.io/football/teams/572.png",
    "Buducnost Podgorica": "https://media.api-sports.io/football/teams/579.png",
    "Alashkert": "https://media.api-sports.io/football/teams/582.png",
    "FK Zalgiris Vilnius": "https://media.api-sports.io/football/teams/586.png",
    "Zenit Saint Petersburg": "https://media.api-sports.io/football/teams/596.png",
    "FK Crvena Zvezda": "https://media.api-sports.io/football/teams/598.png",
    "Shkendija": "https://media.api-sports.io/football/teams/609.png",
    "Dinamo Zagreb": "https://media.api-sports.io/football/teams/620.png",
    "Fola Esch": "https://media.api-sports.io/football/teams/626.png",
    "Sparta Praha": "https://media.api-sports.io/football/teams/628.png",
    "Galatasaray": "https://media.api-sports.io/football/teams/645.png",
    "HJK helsinki": "https://media.api-sports.io/football/teams/649.png",
    "Ferencvarosi TC": "https://media.api-sports.io/football/teams/651.png",
    "Shamrock Rovers": "https://media.api-sports.io/football/teams/652.png",
    "Slovan Bratislava": "https://media.api-sports.io/football/teams/656.png",
    "Kairat Almaty": "https://media.api-sports.io/football/teams/664.png",
    "Lincoln Red Imps FC": "https://media.api-sports.io/football/teams/667.png",
    "Folgore": "https://media.api-sports.io/football/teams/672.png",
    "Prishtina": "https://media.api-sports.io/football/teams/680.png",
    "Flora Tallinn": "https://media.api-sports.io/football/teams/687.png",
    "Genk": "https://media.api-sports.io/football/teams/742.png",
    "Rapid Vienna": "https://media.api-sports.io/football/teams/781.png",
    "CFR 1907 Cluj": "https://media.api-sports.io/football/teams/2246.png",
    "Dinamo Tbilisi": "https://media.api-sports.io/football/teams/2262.png",
    "Neftchi Baku": "https://media.api-sports.io/football/teams/2270.png",
    "Teuta Durr\u00ebs": "https://media.api-sports.io/football/teams/3320.png",
    "Inter Club d'Escaldes": "https://media.api-sports.io/football/teams/3342.png",
    "Borac Banja Luka": "https://media.api-sports.io/football/teams/3364.png",
    "Omonia Nicosia": "https://media.api-sports.io/football/teams/3402.png",
    "Hibernians": "https://media.api-sports.io/football/teams/3884.png",
    "HB": "https://media.api-sports.io/football/teams/4133.png",
    "Maccabi Haifa": "https://media.api-sports.io/football/teams/4195.png",
    "Mura": "https://media.api-sports.io/football/teams/4197.png",
    "Riga": "https://media.api-sports.io/football/teams/10124.png",
    "Austria Vienna": "https://media.api-sports.io/football/teams/601.png",
    "SCR Altach": "https://media.api-sports.io/football/teams/618.png",
    "Sturm Graz": "https://media.api-sports.io/football/teams/637.png",
    "Admira Wacker": "https://media.api-sports.io/football/teams/1023.png",
    "Wolfsberger AC": "https://media.api-sports.io/football/teams/1025.png",
    "Lask Linz": "https://media.api-sports.io/football/teams/1026.png",
    "Ried": "https://media.api-sports.io/football/teams/1028.png",
    "TSV Hartberg": "https://media.api-sports.io/football/teams/1072.png",
    "WSG Wattens": "https://media.api-sports.io/football/teams/1398.png",
    "Austria Klagenfurt": "https://media.api-sports.io/football/teams/1405.png",
    "Lyon": "https://media.api-sports.io/football/teams/80.png",
    "Marseille": "https://media.api-sports.io/football/teams/81.png",
    "ST Johnstone": "https://media.api-sports.io/football/teams/258.png",
    "Randers FC": "https://media.api-sports.io/football/teams/401.png",
    "Lazio": "https://media.api-sports.io/football/teams/487.png",
    "Napoli": "https://media.api-sports.io/football/teams/492.png",
    "Lokomotiv Moscow": "https://media.api-sports.io/football/teams/597.png",
    "Zorya Luhansk": "https://media.api-sports.io/football/teams/599.png",
    "Fenerbahce": "https://media.api-sports.io/football/teams/611.png",
    "Antwerp": "https://media.api-sports.io/football/teams/740.png",
    "FK Jablonec": "https://media.api-sports.io/football/teams/1122.png",
    "Anorthosis": "https://media.api-sports.io/football/teams/2269.png",
    "Atlanta United II": "https://media.api-sports.io/football/teams/3986.png",
    "Birmingham Legion": "https://media.api-sports.io/football/teams/3989.png",
    "Charleston Battery": "https://media.api-sports.io/football/teams/3990.png",
    "Colorado Springs": "https://media.api-sports.io/football/teams/3992.png",
    "El Paso Locomotive": "https://media.api-sports.io/football/teams/3993.png",
    "Hartford Athletic": "https://media.api-sports.io/football/teams/3995.png",
    "Indy Eleven": "https://media.api-sports.io/football/teams/3996.png",
    "LA Galaxy II": "https://media.api-sports.io/football/teams/3997.png",
    "Las Vegas Lights": "https://media.api-sports.io/football/teams/3998.png",
    "Loudoun United": "https://media.api-sports.io/football/teams/3999.png",
    "Louisville City": "https://media.api-sports.io/football/teams/4000.png",
    "Memphis 901": "https://media.api-sports.io/football/teams/4001.png",
    "New Mexico United": "https://media.api-sports.io/football/teams/4003.png",
    "New York RB II": "https://media.api-sports.io/football/teams/4004.png",
    "Orange County SC": "https://media.api-sports.io/football/teams/4007.png",
    "Phoenix Rising": "https://media.api-sports.io/football/teams/4009.png",
    "Pittsburgh Riverhounds": "https://media.api-sports.io/football/teams/4010.png",
    "Rio Grande Valley": "https://media.api-sports.io/football/teams/4014.png",
    "Sacramento Republic": "https://media.api-sports.io/football/teams/4015.png",
    "San Antonio": "https://media.api-sports.io/football/teams/4017.png",
    "Tampa Bay Rowdies": "https://media.api-sports.io/football/teams/4021.png",
    "Tulsa Roughnecks": "https://media.api-sports.io/football/teams/4022.png",
    "Miami FC": "https://media.api-sports.io/football/teams/9030.png",
    "Detroit City": "https://media.api-sports.io/football/teams/9043.png",
    "San Diego Loyal": "https://media.api-sports.io/football/teams/9991.png",
    "Oakland Roots": "https://media.api-sports.io/football/teams/10874.png",
    "Monterey Bay": "https://media.api-sports.io/football/teams/18375.png",
    "Ava\u00ed U23": "https://media.api-sports.io/football/teams/16042.png",
    "CRB U23": "https://media.api-sports.io/football/teams/16043.png",
    "Cear\u00e1 U23": "https://media.api-sports.io/football/teams/16044.png",
    "Corinthians U23": "https://media.api-sports.io/football/teams/16045.png",
    "Coritiba U23": "https://media.api-sports.io/football/teams/16046.png",
    "Fluminense U23": "https://media.api-sports.io/football/teams/16047.png",
    "Fortaleza U23": "https://media.api-sports.io/football/teams/16048.png",
    "Gr\u00eamio U23": "https://media.api-sports.io/football/teams/16049.png",
    "Juventude U23": "https://media.api-sports.io/football/teams/16050.png",
    "RB Bragantino U23": "https://media.api-sports.io/football/teams/16053.png",
    "Santos U23": "https://media.api-sports.io/football/teams/16056.png",
    "Bahia U23": "https://media.api-sports.io/football/teams/16732.png",
    "Cuiab\u00e1 U23": "https://media.api-sports.io/football/teams/16733.png",
    "Figueirense U23": "https://media.api-sports.io/football/teams/16734.png",
    "Ponte Preta U23": "https://media.api-sports.io/football/teams/16735.png",
    "Vit\u00f3ria U23": "https://media.api-sports.io/football/teams/16736.png"
}
